audio_normalizer/__init__.py
audio_normalizer/controller.py
audio_normalizer/normalizer.py
audio_normalizer/user_interface.py
audio_normalizer/utils.py
audio_normalizer/assets/UI.png
audio_normalizer/assets/nor.png
audio_normalizer-1.3.1.dist-info/LICENCE
audio_normalizer-1.3.1.dist-info/METADATA
audio_normalizer-1.3.1.dist-info/WHEEL
audio_normalizer-1.3.1.dist-info/top_level.txt
audio_normalizer-1.3.1.dist-info/RECORD
