Metadata-Version: 2.1
Name: audio-normalizer
Version: 1.3.1
Summary: Audio Normalizer for MP3 and WAV files
Author: Matthias Christopher Schmid
Author-email: Matthias Christopher Schmid <schmid.mat93@gmail.com>
Project-URL: Homepage, https://github.com/MatthiasSchmid93/AudioNormalizer
Project-URL: Bug Tracker, https://github.com/MatthiasSchmid93/AudioNormalizer/issues
Classifier: Programming Language :: Python :: 3
Classifier: License :: OSI Approved :: GNU General Public License v3 (GPLv3)
Classifier: Operating System :: Microsoft :: Windows
Requires-Python: >=3.7
License-File: LICENCE
Requires-Dist: setuptools
Requires-Dist: mutagen (==1.46.0)
Requires-Dist: numpy (==1.21.5)
Requires-Dist: pydub (==0.25.1)
Requires-Dist: PyQt5 (==5.12.3)
Requires-Dist: PySimpleGUI (==4.60.5)
Requires-Dist: scipy (==1.9.1)
Requires-Dist: jsonschema (>=3.2.0)
Requires-Dist: matplotlib (==3.5.2)
